inigo_py/VERSION
inigo_py/__init__.py
inigo_py/ffi.py
inigo_py/query.py
inigo_py/django/__init__.py
inigo_py/django/middleware.py
inigo_py/flask/__init__.py
inigo_py/flask/middleware.py
inigo_py/lib/inigo-darwin-amd64.dylib
inigo_py/lib/inigo-darwin-arm64.dylib
inigo_py/lib/inigo-linux-amd64.so
inigo_py/lib/inigo-linux-arm64.so
inigo_py/lib/inigo-windows-amd64.dll
inigo_py/lib/inigo-windows-arm64.dll
inigo_py-1.3.1.dist-info/licenses/LICENSE
inigo_py-1.3.1.dist-info/METADATA
inigo_py-1.3.1.dist-info/WHEEL
inigo_py-1.3.1.dist-info/top_level.txt
inigo_py-1.3.1.dist-info/RECORD
