Metadata-Version: 2.4
Name: inigo_py
Version: 1.3.1
Summary: Inigo Middleware
Home-page: https://github.com/inigolabs/inigo-py
Author: Nikolai Kaploniuk
Author-email: nkaploniuk@inigo.io
License: MIT
Project-URL: Bug Tracker, https://github.com/inigolabs/inigo-py/issues
Project-URL: Documentation, https://docs.inigo.io
Project-URL: Support, https://slack.inigo.io
Keywords: api graphql inigo graphene
Classifier: Development Status :: 2 - Pre-Alpha
Classifier: License :: OSI Approved :: MIT License
Classifier: Intended Audience :: Developers
Classifier: Topic :: Software Development :: Libraries
Classifier: Programming Language :: Python :: 3
Classifier: Programming Language :: Python :: 3.8
Classifier: Programming Language :: Python :: 3.9
Classifier: Programming Language :: Python :: 3.10
Classifier: Programming Language :: Python :: 3.11
Requires-Python: >= 3.8
License-File: LICENSE
Provides-Extra: all
Requires-Dist: flask<3,>=2; extra == "all"
Requires-Dist: werkzeug<3.0.0,>=2.2.3; extra == "all"
Requires-Dist: django<5,>=4; extra == "all"
Provides-Extra: flask
Requires-Dist: flask<3,>=2; extra == "flask"
Requires-Dist: werkzeug<3.0.0,>=2.2.3; extra == "flask"
Provides-Extra: django
Requires-Dist: django<5,>=4; extra == "django"
Dynamic: author
Dynamic: author-email
Dynamic: classifier
Dynamic: description
Dynamic: description-content-type
Dynamic: home-page
Dynamic: keywords
Dynamic: license
Dynamic: license-file
Dynamic: project-url
Dynamic: provides-extra
Dynamic: requires-python
Dynamic: summary
